uglipy/__init__.py
uglipy-0.1.0a1.dist-info/LICENSE
uglipy-0.1.0a1.dist-info/METADATA
uglipy-0.1.0a1.dist-info/WHEEL
uglipy-0.1.0a1.dist-info/top_level.txt
uglipy-0.1.0a1.dist-info/RECORD
